{
  "fetchedAt": "2026-04-07T14:27:51.586Z",
  "placeId": "ChIJbYTlkMwPNEcRWuXS1vymzcE",
  "rating": 4.5,
  "totalReviews": 30,
  "reviews": [
    {
      "authorName": "Mariia Levchenko",
      "rating": 5,
      "text": "Адвокат Левченко Наталія Вікторівна– майстер своєї справи! Завдяки її знанням, ми швидко вирішили моє питання. Відмінна робота, висока відповідальність і повна віддача. Дуже вдячна! Рекомендую!",
      "relativeTimeDescription": "5 місяців тому"
    },
    {
      "authorName": "Василь Тимчасюк",
      "rating": 5,
      "text": "Професійний адвокат.дякую за допомогу, дуже швидко вирішена справа. Рекомендую!",
      "relativeTimeDescription": "6 місяців тому"
    },
    {
      "authorName": "Марьянка Кочала",
      "rating": 5,
      "text": "Хороша і чуйна людина яка допоможе і завжди!Як адвокат завжи майстер свого діла",
      "relativeTimeDescription": "5 місяців тому"
    },
    {
      "authorName": "Мар'яна Сивочола",
      "rating": 5,
      "text": "Дуже сподобалося спілкування. Чудовий фахівець. Питання було зрозуміло роз'яснено. Дякую. Рекомендую.",
      "relativeTimeDescription": "6 місяців тому"
    }
  ]
}